pyemvue/__init__.py
pyemvue/__main__.py
pyemvue/__version__.py
pyemvue/auth.py
pyemvue/customer.py
pyemvue/device.py
pyemvue/enums.py
pyemvue/pyemvue.py
pyemvue-0.18.9.dist-info/METADATA
pyemvue-0.18.9.dist-info/WHEEL
pyemvue-0.18.9.dist-info/licenses/LICENSE.txt
pyemvue-0.18.9.dist-info/RECORD
